siemens_plc/__init__.py
siemens_plc/exception.py
siemens_plc/s7_plc.py
siemens_plc-1.7.0.dist-info/METADATA
siemens_plc-1.7.0.dist-info/WHEEL
siemens_plc-1.7.0.dist-info/RECORD
