Metadata-Version: 2.4
Name: siemens-plc
Version: 1.7.0
Summary: 西门子plc通讯
Author: LiuWei
Author-email: 183074632@qq.com
Requires-Python: >=3.11,<4.0
Classifier: Programming Language :: Python :: 3
Classifier: Programming Language :: Python :: 3.11
Classifier: Programming Language :: Python :: 3.12
Classifier: Programming Language :: Python :: 3.13
Classifier: Programming Language :: Python :: 3.14
Requires-Dist: python-snap7 (>=2.0.2,<3.0.0)
